flask_parameters/__init__.py
flask_parameters/app.py
flask_parameters/exceptions.py
flask_parameters/flask_helpers.py
flask_parameters/type_checking.py
flask_parameters-0.1.0.dist-info/LICENSE.txt
flask_parameters-0.1.0.dist-info/METADATA
flask_parameters-0.1.0.dist-info/WHEEL
flask_parameters-0.1.0.dist-info/top_level.txt
flask_parameters-0.1.0.dist-info/RECORD
