Metadata-Version: 2.2
Name: flask-parameters
Version: 0.1.0
Project-URL: Homepage, https://github.com/millarcalder/flask_params
Keywords: flask
Classifier: License :: OSI Approved :: MIT License
Classifier: Programming Language :: Python :: 3
Requires-Python: >=3.7
License-File: LICENSE.txt
Requires-Dist: flask
